APB_slave.sv
module APB_slave
#(parameter number_in_group_ADDR = 4'h0, // адрес регистра, где хранится номер студента в группе
parameter data_ADDR = 4'h4,              // адрес регистра, где хранится дата дд.мм.гг
parameter surname_ADDR = 4'h8,           // адрес регистра, где хранится первые 4 буквы фамилии
parameter name_ADDDR = 4'hC)             // адрес регистра, где хранится первые 4 буквы имени

(
    input wire PWRITE,            // сигнал, выбирающий режим записи или чтения (1 - запись, 0 - чтение)
    input wire PCLK,              // сигнал синхронизации
    input wire PSEL,              // сигнал выбора переферии 
    input wire [31:0] PADDR,      // Адрес регистра
    input wire [31:0] PWDATA,     // Данные для записи в регистр
    output reg [31:0] PRDATA = 0,     // Данные, прочитанные из регистра
    input wire PENABLE,           // сигнал разрешения
    output reg PREADY = 0             // сигнал готовности (флаг того, что всё сделано успешно)
);



//Регистры для записи значений
reg [31:0] number_in_group = 0;
reg [31:0] data = 0;
reg [31:0] surname = 0;
reg [31:0] name = 0;

// циклы записи и чтения интерфейса APB

always @(posedge PSEL or posedge PCLK) 
begin
    
    if (PSEL && !PWRITE && PENABLE) // Чтение из регистров 
     begin
        case(PADDR)
         4'h0: PRDATA <= number_in_group;
         4'h4: PRDATA <= data;
         4'h8: PRDATA <= surname;
         4'hC: PRDATA <= name;
        endcase
        PREADY <= 1'd1;            // поднимаем флаг заверешения операции
     end

    
    else if (PSEL && PWRITE && PENABLE) // Запись в регистры
     begin
        case(PADDR)
         4'h0: number_in_group <= PWDATA; // запись по адресу регистра номера человека в группе
         4'h4: data <= PWDATA;            // запись по адресу регистра даты
         4'h8: surname <= PWDATA;         // запись по адресу регистра фамилии
         4'hC: name <= PWDATA;            // запись по адресу регистра имени
        endcase
        PREADY <= 1'd1;   // поднимаем флаг заверешения операции
     end

   
   if (PREADY) // сбрасываем PREADY после выполнения записи или чтения
    begin
      $display();
      $display("Operation: %b", PWRITE);
      $display("Address: %h", PADDR);

      if(PWRITE)
      begin
        $display("Data for recording: %h", PWDATA);
      end

      else if(!PWRITE)
      begin
        $display("Read data: %h", PRDATA);
      end

      PREADY <= !PREADY;
    end

	
  end


endmodule

APB_master.sv
module APB_master
(
    input wire PCLK,                    // сигнал синхронизации
    input wire PWRITE_MASTER,           // сигнал, выбирающий режим записи или чтения (1 - запись, 0 - чтение)
    output reg PSEL = 0,                // сигнал выбора переферии 
    input wire [31:0] PADDR_MASTER,     // Адрес регистра
    input wire [31:0] PWDATA_MASTER,    // Данные для записи в регистр
    output reg [31:0] PRDATA_MASTER = 0,// Данные, прочитанные из слейва
    output reg PENABLE = 0,             // сигнал разрешения, формирующийся в мастер APB
    input wire PRESET,                  // сигнал сброса
    input wire PREADY,                  // сигнал готовности (флаг того, что всё сделано успешно)
    output reg [31:0] PADDR = 0,        // адрес, который мы будем передавать в слейв
    output reg [31:0] PWDATA = 0,       // данные, которые будут передаваться в слейв,
    input  wire [31:0] PRDATA,          // данные, прочтённые с слейва
    output reg PWRITE = 0               // сигнал записи или чтения на вход слейва
);

task apb_write; // функция записи
input  [31:0] inp_addr;
input  [31:0] inp_data;
begin
  PADDR = inp_addr;   // передаем адрес на входе мастера в слейв
  PWDATA = inp_data;  // передаём данные в слейв
  PWRITE = 1'd1;      // ставим сигнал записи
  PSEL = 1'd1;        // поднимаем флаг выбора устройства
  PENABLE = 1'd1;     // выдаём разрешение на выполнение действий

  if(PREADY)
   begin
     PSEL = !PSEL;        // убираем сигнал psel
     PENABLE = !PENABLE; // убираем  сигнал PENABLE
   end
end
endtask

task apb_read; //функция чтения из слейва
input [31:0] inp_addr;
begin
  if(!PREADY)
  begin
    PADDR = inp_addr; // передаем адрес на входе мастера в слейв
    PWRITE = 1'd0;
    PSEL = 1'd1;
    PENABLE = 1'd1;
  end
  
  else if(PREADY)
   begin
     PSEL = !PSEL;
     PENABLE = !PENABLE;
   end
end
endtask

// циклы записи и чтения интерфейса APB
always @(posedge PCLK) 
begin
    if(PRESET) // если поднят сигнал сброса
    begin
      PADDR <= 32'b0;
      PWDATA <= 32'b0;
      PWRITE <= 1'b0;
      PSEL <= 1'b0;
      PENABLE <= 1'b0;
      PRDATA_MASTER <= 1'b0;
    end

    else if (!PWRITE_MASTER) // Чтение из регистров 
     begin
        apb_read(PADDR_MASTER); // вызов фунции чтения
     end
    else if (PWRITE_MASTER) // Запись в регистры
     begin
        apb_write(PADDR_MASTER, PWDATA_MASTER);
     end
  end

always @(posedge PREADY) // если pready поднялся в 1
begin
  if (!PWRITE_MASTER)     // если выбрана операция чтение
    begin
     PRDATA_MASTER <=PRDATA; // передаём данные на выход apb мастера
    end
end
endmodule

APB_master_tb.sv
`include "APB_master.sv"
`include "APB_slave.sv"
module APB_master_tb;



reg PCLK = 0;                   // сигнал синхронизации
reg PWRITE_MASTER = 0;          // сигнал, выбирающий режим записи или чтения (1 - запись, 0 - чтение)
wire PSEL;                      // сигнал выбора переферии 
reg [31:0] PADDR_MASTER = 0;    // Адрес регистра
reg [31:0] PWDATA_MASTER = 0;   // Данные для записи в регистр
wire [31:0] PRDATA_MASTER;       // Данные, прочитанные из слейва
wire PENABLE;                    // сигнал разрешения, формирующийся в мастер APB
reg PRESET = 0;                   // сигнал сброса
wire PREADY;                      // сигнал готовности (флаг того, что всё сделано успешно)
wire [31:0] PADDR;                // адрес, который мы будем передавать в слейв
wire [31:0] PWDATA;               // данные, которые будут передаваться в слейв,
wire [31:0] PRDATA ;              // данные, прочтённые с слейва
wire PWRITE;                      // сигнал записи или чтения на вход слейва

APB_master APB_master_1 (
    .PCLK(PCLK),
    .PWRITE_MASTER(PWRITE_MASTER),
    .PSEL(PSEL),
    .PADDR_MASTER(PADDR_MASTER),
    .PWDATA_MASTER(PWDATA_MASTER),
    .PRDATA_MASTER(PRDATA_MASTER),
    .PENABLE(PENABLE),
    .PRESET(PRESET),
    .PREADY(PREADY),
    .PADDR(PADDR),
    .PWDATA(PWDATA),
    .PRDATA(PRDATA),
    .PWRITE(PWRITE)
);

APB_slave APB_slave_1 (
    .PWRITE(PWRITE),
    .PSEL(PSEL),
    .PADDR(PADDR),
    .PWDATA(PWDATA),
    .PRDATA(PRDATA),
    .PENABLE(PENABLE),
    .PREADY(PREADY),
    .PCLK(PCLK)
);



always #200 PCLK = ~PCLK; // генерация входного сигнала Pclk

initial begin
//ЗАПИСЬ
PCLK = 0;
PWRITE_MASTER = 1;         // выбираем запись
PWDATA_MASTER = 25;         // в данные для записи записываем 19
PADDR_MASTER = 0;           // выбираем адрес регистра number_in_group
@(posedge PCLK);
@(posedge PCLK);

PWRITE_MASTER = 1;         // выбираем запись
PWDATA_MASTER = 32'h24122023; // в данные для записи записываем 24.12.2023
PADDR_MASTER = 4;           // выбираем адрес регистра date
@(posedge PCLK);
@(posedge PCLK);

PWRITE_MASTER = 1;         // выбираем запись
PWDATA_MASTER = 32'hCFEEF6E5; // в данные для записи записываем первые 4 буквы фамилии в аски коде
PADDR_MASTER = 8;           // выбираем адрес регистра surname
@(posedge PCLK);
@(posedge PCLK);

PWRITE_MASTER = 1;            // выбираем запись
PWDATA_MASTER = 32'hC2EEE2E0;  // в данные для записи записываем первые 4 буквы имени в аски коде
PADDR_MASTER = 4'hC;           // выбираем адрес регистра name
@(posedge PCLK);
@(posedge PCLK);


//ЧТЕНИЕ
PWRITE_MASTER = 0;            // выбираем чтение
PADDR_MASTER = 0;           // выбираем адрес регистра номера в группе
@(posedge PCLK);
@(posedge PCLK);


PWRITE_MASTER = 0;            // выбираем чтение
PADDR_MASTER = 4;          // выбираем адрес регистра date
@(posedge PCLK);
@(posedge PCLK);

PWRITE_MASTER = 0;            // выбираем чтение
PADDR_MASTER = 8;            // выбираем адрес регистра surname
@(posedge PCLK);
@(posedge PCLK);

PWRITE_MASTER = 0;            // выбираем чтение
PADDR_MASTER = 4'hC;           // выбираем адрес регистра name
@(posedge PCLK);
@(posedge PCLK);




 #500 $finish; // Заканчиваем симуляцию
end







initial begin
$dumpfile("APB_master.vcd"); // создание файла для сохранения результатов симуляции
$dumpvars(0, APB_master_tb); // установка переменных для сохранения в файле
$dumpvars;
end


endmodule

APB_master.vcd
$date
	Wed Dec 27 22:32:07 2023
$end
$version
	Icarus Verilog
$end
$timescale
	1s
$end
$scope module APB_master_tb $end
$var wire 32 ! PADDR [31:0] $end
$var wire 1 " PENABLE $end
$var wire 32 # PRDATA [31:0] $end
$var wire 32 $ PRDATA_MASTER [31:0] $end
$var wire 1 % PREADY $end
$var wire 1 & PSEL $end
$var wire 32 ' PWDATA [31:0] $end
$var wire 1 ( PWRITE $end
$var reg 32 ) PADDR_MASTER [31:0] $end
$var reg 1 * PCLK $end
$var reg 1 + PRESET $end
$var reg 32 , PWDATA_MASTER [31:0] $end
$var reg 1 - PWRITE_MASTER $end
$scope module APB_master_1 $end
$var wire 32 . PADDR_MASTER [31:0] $end
$var wire 1 / PCLK $end
$var wire 32 0 PRDATA [31:0] $end
$var wire 1 % PREADY $end
$var wire 1 1 PRESET $end
$var wire 32 2 PWDATA_MASTER [31:0] $end
$var wire 1 3 PWRITE_MASTER $end
$var reg 32 4 PADDR [31:0] $end
$var reg 1 5 PENABLE $end
$var reg 32 6 PRDATA_MASTER [31:0] $end
$var reg 1 7 PSEL $end
$var reg 32 8 PWDATA [31:0] $end
$var reg 1 9 PWRITE $end
$scope task apb_read $end
$var reg 32 : inp_addr [31:0] $end
$upscope $end
$scope task apb_write $end
$var reg 32 ; inp_addr [31:0] $end
$var reg 32 < inp_data [31:0] $end
$upscope $end
$upscope $end
$scope module APB_slave_1 $end
$var wire 32 = PADDR [31:0] $end
$var wire 1 / PCLK $end
$var wire 1 " PENABLE $end
$var wire 1 & PSEL $end
$var wire 32 > PWDATA [31:0] $end
$var wire 1 ( PWRITE $end
$var reg 32 ? PRDATA [31:0] $end
$var reg 1 @ PREADY $end
$var reg 32 A data [31:0] $end
$var reg 32 B name [31:0] $end
$var reg 32 C number_in_group [31:0] $end
$var reg 32 D surname [31:0] $end
$upscope $end
$upscope $end
$scope module APB_master_tb $end
$scope module APB_master_1 $end
$scope task apb_read $end
$upscope $end
$scope task apb_write $end
$upscope $end
$upscope $end
$scope module APB_slave_1 $end
$upscope $end
$upscope $end
$enddefinitions $end
#0
$dumpvars
b0 D
b0 C
b0 B
b0 A
0@
b0 ?
b0 >
b0 =
bx <
bx ;
bx :
09
b0 8
07
b0 6
05
b0 4
13
b11001 2
01
b0 0
0/
b0 .
1-
b11001 ,
0+
0*
b0 )
0(
b0 '
0&
0%
b0 $
b0 #
0"
b0 !
$end
#200
1@
1%
b11001 C
15
1"
17
1&
19
1(
b11001 8
b11001 '
b11001 >
b11001 <
b0 ;
1*
1/
#400
0*
0/
#600
0@
0%
05
0"
07
0&
b100 )
b100 .
b100100000100100010000000100011 ,
b100100000100100010000000100011 2
1*
1/
#800
0*
0/
#1000
1@
1%
b100100000100100010000000100011 A
15
1"
17
1&
b100100000100100010000000100011 8
b100100000100100010000000100011 '
b100100000100100010000000100011 >
b100 4
b100 !
b100 =
b100100000100100010000000100011 <
b100 ;
1*
1/
#1200
0*
0/
#1400
0@
0%
05
0"
07
0&
b1000 )
b1000 .
b11001111111011101111011011100101 ,
b11001111111011101111011011100101 2
1*
1/
#1600
0*
0/
#1800
1@
1%
b11001111111011101111011011100101 D
15
1"
17
1&
b11001111111011101111011011100101 8
b11001111111011101111011011100101 '
b11001111111011101111011011100101 >
b1000 4
b1000 !
b1000 =
b11001111111011101111011011100101 <
b1000 ;
1*
1/
#2000
0*
0/
#2200
0@
0%
05
0"
07
0&
b1100 )
b1100 .
b11000010111011101110001011100000 ,
b11000010111011101110001011100000 2
1*
1/
#2400
0*
0/
#2600
1@
1%
b11000010111011101110001011100000 B
15
1"
17
1&
b11000010111011101110001011100000 8
b11000010111011101110001011100000 '
b11000010111011101110001011100000 >
b1100 4
b1100 !
b1100 =
b11000010111011101110001011100000 <
b1100 ;
1*
1/
#2800
0*
0/
#3000
0@
0%
05
0"
07
0&
b0 )
b0 .
0-
03
1*
1/
#3200
0*
0/
#3400
b11001 6
b11001 $
1@
1%
b11001 ?
b11001 #
b11001 0
15
1"
17
1&
09
0(
b0 4
b0 !
b0 =
b0 :
1*
1/
#3600
0*
0/
#3800
0@
0%
05
0"
07
0&
b100 )
b100 .
1*
1/
#4000
0*
0/
#4200
b100100000100100010000000100011 6
b100100000100100010000000100011 $
1@
1%
b100100000100100010000000100011 ?
b100100000100100010000000100011 #
b100100000100100010000000100011 0
15
1"
17
1&
b100 4
b100 !
b100 =
b100 :
1*
1/
#4400
0*
0/
#4600
0@
0%
05
0"
07
0&
b1000 )
b1000 .
1*
1/
#4800
0*
0/
#5000
b11001111111011101111011011100101 6
b11001111111011101111011011100101 $
1@
1%
b11001111111011101111011011100101 ?
b11001111111011101111011011100101 #
b11001111111011101111011011100101 0
15
1"
17
1&
b1000 4
b1000 !
b1000 =
b1000 :
1*
1/
#5200
0*
0/
#5400
0@
0%
05
0"
07
0&
b1100 )
b1100 .
1*
1/
#5600
0*
0/
#5800
b11000010111011101110001011100000 6
b11000010111011101110001011100000 $
1@
1%
b11000010111011101110001011100000 ?
b11000010111011101110001011100000 #
b11000010111011101110001011100000 0
15
1"
17
1&
b1100 4
b1100 !
b1100 =
b1100 :
1*
1/
#6000
0*
0/
#6200
0@
0%
05
0"
07
0&
1*
1/
#6400
0*
0/
#6600
1@
1%
15
1"
17
1&
1*
1/
